turicreate/__dummy.cpython-35m-x86_64-linux-gnu.so
turicreate/__init__.py
turicreate/_gl_pickle.py
turicreate/_json.py
turicreate/_sys_util.py
turicreate/aggregate.py
turicreate/extensions.py
turicreate/libadditional_sframe_utilities.so
turicreate/libcontent_interpretation_extensions.so
turicreate/libcoreml_extension.so
turicreate/libdictionary_transformation_extensions.so
turicreate/libinternal_demo.so
turicreate/libjson.so
turicreate/libunity_shared.so
turicreate/libxgboost_extension.so
turicreate/version_info.py
turicreate/Turi Create Visualization/cef.pak
turicreate/Turi Create Visualization/cef_100_percent.pak
turicreate/Turi Create Visualization/cef_200_percent.pak
turicreate/Turi Create Visualization/cef_extensions.pak
turicreate/Turi Create Visualization/devtools_resources.pak
turicreate/Turi Create Visualization/icudtl.dat
turicreate/Turi Create Visualization/libEGL.so
turicreate/Turi Create Visualization/libGLESv2.so
turicreate/Turi Create Visualization/libcef.so
turicreate/Turi Create Visualization/natives_blob.bin
turicreate/Turi Create Visualization/snapshot_blob.bin
turicreate/Turi Create Visualization/v8_context_snapshot.bin
turicreate/Turi Create Visualization/visualization_client
turicreate/Turi Create Visualization/html/asset-manifest.json
turicreate/Turi Create Visualization/html/favicon.ico
turicreate/Turi Create Visualization/html/index.css
turicreate/Turi Create Visualization/html/index.html
turicreate/Turi Create Visualization/html/index.js
turicreate/Turi Create Visualization/html/precache-manifest.c66015a7f5bf66b84f33da94524faacd.js
turicreate/Turi Create Visualization/html/service-worker.js
turicreate/Turi Create Visualization/html/static/css/main.a7482690.chunk.css
turicreate/Turi Create Visualization/html/static/css/main.a7482690.chunk.css.map
turicreate/Turi Create Visualization/html/static/js/1.59710461.chunk.js
turicreate/Turi Create Visualization/html/static/js/1.59710461.chunk.js.map
turicreate-6.4.1.dist-info/LICENSE.txt
turicreate-6.4.1.dist-info/METADATA
turicreate-6.4.1.dist-info/WHEEL
turicreate-6.4.1.dist-info/top_level.txt
turicreate-6.4.1.dist-info/RECORD
