Metadata-Version: 2.1
Name: turicreate
Version: 6.4.1
Summary: Turi Create simplifies the development of custom machine learning models.
Home-page: https://github.com/apple/turicreate
Author: Apple Inc.
Author-email: turi-create@group.apple.com
License: LICENSE.txt
Platform: UNKNOWN
Classifier: Development Status :: 5 - Production/Stable
Classifier: Environment :: Console
Classifier: Intended Audience :: Developers
Classifier: Intended Audience :: Financial and Insurance Industry
Classifier: Intended Audience :: Information Technology
Classifier: Intended Audience :: Other Audience
Classifier: Intended Audience :: Science/Research
Classifier: License :: OSI Approved :: BSD License
Classifier: Natural Language :: English
Classifier: Programming Language :: Python :: 2.7
Classifier: Programming Language :: Python :: 3.5
Classifier: Programming Language :: Python :: 3.6
Classifier: Programming Language :: Python :: 3.7
Classifier: Programming Language :: Python :: 3.8
Classifier: Programming Language :: Python :: Implementation :: CPython
Classifier: Topic :: Scientific/Engineering
Classifier: Topic :: Scientific/Engineering :: Information Analysis
Classifier: Operating System :: POSIX :: Linux
Classifier: Operating System :: POSIX :: BSD
Classifier: Operating System :: Unix
Requires-Dist: decorator (>=4.0.9)
Requires-Dist: numpy
Requires-Dist: pandas (>=0.23.2)
Requires-Dist: pillow (>=5.2.0)
Requires-Dist: prettytable (==0.7.2)
Requires-Dist: resampy (==0.2.1)
Requires-Dist: requests (>=2.9.1)
Requires-Dist: scipy (>=1.1.0)
Requires-Dist: six (>=1.10.0)
Requires-Dist: llvmlite (==0.31.0)
Requires-Dist: coremltools (==3.3)
Requires-Dist: tensorflow (<2.1.0,>=2.0.0)
Requires-Dist: numba (<0.51.0)
